boilermaker/__init__.py
boilermaker/app.py
boilermaker/config.py
boilermaker/failure.py
boilermaker/retries.py
boilermaker/sample.py
boilermaker/service_bus.py
boilermaker/task.py
boilermaker/tracing.py
boilermaker_servicebus-0.8.0.dist-info/licenses/LICENSE
examples/basic.py
examples/callbacks.py
tests/conftest.py
tests/test_app.py
tests/test_config.py
tests/test_retries.py
tests/test_sample.py
tests/test_service_bus.py
tests/test_task.py
boilermaker_servicebus-0.8.0.dist-info/METADATA
boilermaker_servicebus-0.8.0.dist-info/WHEEL
boilermaker_servicebus-0.8.0.dist-info/top_level.txt
boilermaker_servicebus-0.8.0.dist-info/RECORD
