Metadata-Version: 2.4
Name: boilermaker-servicebus
Version: 0.8.0
Summary: An async python Background task system using Azure Service Bus Queues
Author-email: Erik Aker <eaker@mulliganfunding.com>
License:                                  Apache License
Project-URL: Documentation, https://mulliganfunding.github.io/boilermaker-servicebus/
Project-URL: Repository, https://github.com/MulliganFunding/boilermaker-servicebus
Project-URL: Issues, https://github.com/MulliganFunding/boilermaker-servicebus/issues
Requires-Python: >=3.11
License-File: LICENSE
Requires-Dist: aio-azure-clients-toolbox>=0.4.0
Requires-Dist: anyio>=4.7.0
Requires-Dist: azure-core-tracing-opentelemetry>=1.0.0b12
Requires-Dist: azure-servicebus>=7.12.3
Requires-Dist: azure-identity>=1.21.0
Requires-Dist: opentelemetry-api>=1.34.0
Requires-Dist: pydantic>=2.10.3
Requires-Dist: pydantic-settings>=2.8.0
Requires-Dist: uuid-utils>=0.11.0
Dynamic: license-file
